cryptography-stubs/METADATA.toml
cryptography-stubs/__init__.pyi
cryptography-stubs/exceptions.pyi
cryptography-stubs/fernet.pyi
cryptography-stubs/hazmat/__init__.pyi
cryptography-stubs/hazmat/backends/__init__.pyi
cryptography-stubs/hazmat/backends/interfaces.pyi
cryptography-stubs/hazmat/bindings/__init__.pyi
cryptography-stubs/hazmat/bindings/openssl/__init__.pyi
cryptography-stubs/hazmat/bindings/openssl/binding.pyi
cryptography-stubs/hazmat/primitives/__init__.pyi
cryptography-stubs/hazmat/primitives/cmac.pyi
cryptography-stubs/hazmat/primitives/constant_time.pyi
cryptography-stubs/hazmat/primitives/hashes.pyi
cryptography-stubs/hazmat/primitives/hmac.pyi
cryptography-stubs/hazmat/primitives/keywrap.pyi
cryptography-stubs/hazmat/primitives/padding.pyi
cryptography-stubs/hazmat/primitives/poly1305.pyi
cryptography-stubs/hazmat/primitives/asymmetric/__init__.pyi
cryptography-stubs/hazmat/primitives/asymmetric/dh.pyi
cryptography-stubs/hazmat/primitives/asymmetric/dsa.pyi
cryptography-stubs/hazmat/primitives/asymmetric/ec.pyi
cryptography-stubs/hazmat/primitives/asymmetric/ed25519.pyi
cryptography-stubs/hazmat/primitives/asymmetric/ed448.pyi
cryptography-stubs/hazmat/primitives/asymmetric/padding.pyi
cryptography-stubs/hazmat/primitives/asymmetric/rsa.pyi
cryptography-stubs/hazmat/primitives/asymmetric/utils.pyi
cryptography-stubs/hazmat/primitives/asymmetric/x25519.pyi
cryptography-stubs/hazmat/primitives/asymmetric/x448.pyi
cryptography-stubs/hazmat/primitives/ciphers/__init__.pyi
cryptography-stubs/hazmat/primitives/ciphers/aead.pyi
cryptography-stubs/hazmat/primitives/ciphers/algorithms.pyi
cryptography-stubs/hazmat/primitives/ciphers/modes.pyi
cryptography-stubs/hazmat/primitives/kdf/__init__.pyi
cryptography-stubs/hazmat/primitives/kdf/concatkdf.pyi
cryptography-stubs/hazmat/primitives/kdf/hkdf.pyi
cryptography-stubs/hazmat/primitives/kdf/kbkdf.pyi
cryptography-stubs/hazmat/primitives/kdf/pbkdf2.pyi
cryptography-stubs/hazmat/primitives/kdf/scrypt.pyi
types_cryptography-3.3.22.dist-info/METADATA
types_cryptography-3.3.22.dist-info/WHEEL
types_cryptography-3.3.22.dist-info/top_level.txt
types_cryptography-3.3.22.dist-info/RECORD
